failtrace/__init__.py
failtrace/__main__.py
failtrace/analysis/__init__.py
failtrace/analysis/critical_path_extractor.py
failtrace/analysis/function_extractor.py
failtrace/analysis/locator.py
failtrace/analysis/mapper.py
failtrace/analysis/summarizer.py
failtrace/cli/__init__.py
failtrace/cli/main.py
failtrace/graph/__init__.py
failtrace/graph/builder/__init__.py
failtrace/graph/builder/base.py
failtrace/graph/builder/csharp_graph.py
failtrace/graph/builder/csharp_graph_builder.py
failtrace/graph/builder/detector.py
failtrace/graph/builder/java_graph.py
failtrace/graph/builder/java_graph_builder.py
failtrace/graph/builder/plugins.py
failtrace/graph/builder/python_graph.py
failtrace/graph/builder/python_graph_builder.py
failtrace/graph/utils/__init__.py
failtrace/graph/utils/locator_ranker.py
failtrace/graph/utils/node_summarizer.py
failtrace/graph/utils/path_enricher.py
failtrace/llm/__init__.py
failtrace/llm/avalai_client.py
failtrace/llm/few_shots/__init__.py
failtrace/llm/few_shots/csharp.json
failtrace/llm/few_shots/java.json
failtrace/llm/few_shots/python.json
failtrace/llm/few_shots_loader.py
failtrace/llm/prompt_generator.py
failtrace/llm/structured_prompt_builder.py
failtrace/output/analysis_report.txt
failtrace/output/cache/graph.pkl
failtrace/output/final_prompt.txt
failtrace/output/function_summaries.json
failtrace/output/graph.html
failtrace/output/llm_prompt.json
failtrace/output/summary.json
failtrace/report/__init__.py
failtrace/report/app.css
failtrace/report/app.js
failtrace/report/report_template.html
failtrace/utils/__init__.py
failtrace/utils/file_ops.py
failtrace/utils/logs_parser.py
failtrace/utils/normalize.py
failtrace/utils/report_renderer.py
failtrace/utils/visualizer.py
failtrace-0.7.1.dist-info/entry_points.txt
failtrace-0.7.1.dist-info/METADATA
failtrace-0.7.1.dist-info/WHEEL
failtrace-0.7.1.dist-info/RECORD
